{"sections":{"main":{"type":"main-cart","settings":{}},"17212123985da5e12b":{"type":"apps","blocks":{"sprout_plant_trees_cart_badge_f3BRcn":{"type":"shopify:\/\/apps\/sprout-plant-trees\/blocks\/cart-badge\/7db5ee24-2195-4099-b98e-1547c600e4aa","settings":{"refresh_on_toggle":false}}},"block_order":["sprout_plant_trees_cart_badge_f3BRcn"],"settings":{"full_width":false,"space_around":true}},"recently-viewed":{"type":"recently-viewed","settings":{}}},"order":["main","17212123985da5e12b","recently-viewed"]}