{"sections":{"main":{"type":"main-product","blocks":{"1f6d7fb1-39d1-410a-b202-c5edba49b6be":{"type":"shopify:\/\/apps\/yotpo-product-reviews-ugc\/blocks\/star-rating\/eb7dfd7d-db44-4334-bc49-c893b51b36cf","settings":{"product":"{{product}}"}},"variant_picker":{"type":"variant_picker","settings":{"variant_labels":true,"picker_type":"button","product_dynamic_variants_enable":true,"color_swatches":true}},"price":{"type":"price","settings":{}},"sales_point":{"type":"sales_point","settings":{"icon":"leaf","text":"Eco-plywood with natural wood glue"}},"sales_point2":{"type":"sales_point","settings":{"icon":"checkmark","text":"Taxes & duties are included for the United States, CA, the UK, and the EU Union 🇪🇺"}},"32d70e90-7839-42bd-bb22-5e7077f3fe05":{"type":"sales_point","settings":{"icon":"package","text":"Free delivery within 2 to 4 days in the United States and Canada"}},"sales_point4":{"type":"sales_point","settings":{"icon":"lock","text":"Secure payments and free returns 30 days"}},"inventory_status":{"type":"inventory_status","settings":{"inventory_threshold":20,"inventory_transfers_enable":true}},"buy_buttons":{"type":"buy_buttons","settings":{"show_dynamic_checkout":true,"surface_pickup_enable":true,"show_gift_card_recipient":true}},"0d348e48-1319-41d6-98f1-63874e5b37af":{"type":"shopify:\/\/apps\/tolstoy-shoppable-video-ugc\/blocks\/stories-block\/06fa8282-42ff-403e-b67c-1936776aed11","settings":{"publishId":"doukudvzmw302"}}},"block_order":["1f6d7fb1-39d1-410a-b202-c5edba49b6be","variant_picker","price","sales_point","sales_point2","32d70e90-7839-42bd-bb22-5e7077f3fe05","sales_point4","inventory_status","buy_buttons","0d348e48-1319-41d6-98f1-63874e5b37af"],"disabled":true,"settings":{"image_position":"left","image_container_size":"large","product_image_size":"square","product_zoom_enable":false,"thumbnail_position":"beside","thumbnail_height":"fixed","thumbnail_arrows":true,"mobile_layout":"partial","enable_video_looping":false,"product_video_style":"muted"}},"sub":{"type":"product-full-width","blocks":{"070f4c3d-babb-4fa9-9497-adfc39eea9bf":{"type":"shopify:\/\/apps\/rebuy-personalization-engine\/blocks\/rebuy-widget\/a26ae9b9-933b-40bf-bbc6-bf1220bbc4dc","disabled":true,"settings":{"enabled":true,"id":"118303","product_id_enabled":true,"collection_id_enabled":false}},"description":{"type":"description","settings":{"is_tab":false}}},"block_order":["070f4c3d-babb-4fa9-9497-adfc39eea9bf","description"],"disabled":true,"settings":{"max_width":false}},"1700591428fe934e1e":{"type":"apps","settings":{"full_width":false,"space_around":false}},"slideshow_split_iM3mVC":{"type":"slideshow-split","blocks":{"slide_3gjG6N":{"type":"slide","settings":{"top_subheading":"","title":"5in1 Montessori Climbing Frame Set","title_size":51,"subheading":"Triangle Ladder + Arch\/Rocker + Slide Board\/Ramp + Netting rope + Cushion","link":"","link_text":"","link_2":"","link_text_2":"","text_position":"right","image":"shopify:\/\/shop_images\/5in1-montessori-climbing-frame-set-triangle-ladder-archrocker-slide-boardramp-netting-rope-cushion-3-min.jpg","indent_image":false,"color_scheme":"2"}},"slide_Dm899w":{"type":"slide","disabled":true,"settings":{"top_subheading":"","title":"Highlight products","title_size":60,"subheading":"Repurpose your product photography with our \"Indented\" image option","link":"","link_text":"Optional button","link_2":"","link_text_2":"","text_position":"left","indent_image":true,"color_scheme":"1"}}},"block_order":["slide_3gjG6N","slide_Dm899w"],"settings":{"full_width":true,"height":600,"height_mobile":450,"style":"arrows","autoplay":true,"autoplay_speed":7}},"scrolling_text_A4EmxT":{"type":"scrolling-text","settings":{"text":"Free shipping and returns","link":"","text_size":30,"text_spacing":true,"direction":"left","speed":200,"color_scheme":"1"}},"featured_product_jLmbaE":{"type":"featured-product","blocks":{"yotpo_product_reviews_ugc_star_rating_LEpabf":{"type":"shopify:\/\/apps\/yotpo-product-reviews-ugc\/blocks\/star-rating\/eb7dfd7d-db44-4334-bc49-c893b51b36cf","settings":{}},"price_3i7ebC":{"type":"price","settings":{}},"description_N43Pr4":{"type":"description","disabled":true,"settings":{"is_tab":false}},"variant_picker_WXCTdR":{"type":"variant_picker","disabled":true,"settings":{"variant_labels":true,"picker_type":"button","product_dynamic_variants_enable":true,"color_swatches":false}},"buy_buttons_A9DyAT":{"type":"buy_buttons","settings":{"show_dynamic_checkout":true,"surface_pickup_enable":true,"show_gift_card_recipient":false}}},"block_order":["yotpo_product_reviews_ugc_star_rating_LEpabf","price_3i7ebC","description_N43Pr4","variant_picker_WXCTdR","buy_buttons_A9DyAT"],"settings":{"divider":false,"image_position":"left","image_container_size":"medium","product_image_size":"square","product_zoom_enable":false,"thumbnail_position":"below","thumbnail_arrows":false,"mobile_layout":"partial","enable_video_looping":true,"product_video_style":"muted"}},"advanced_content_HUw6yc":{"type":"advanced-content","blocks":{"liquid_d6CjgP":{"type":"liquid","settings":{"code":"<div class=\"product-block product-block--sales-point\">\n                        <ul class=\"sales-points\">\n                          <li class=\"sales-point\">\n                            <span class=\"icon-and-text\">\n                               <svg aria-hidden=\"true\" focusable=\"false\" role=\"presentation\" class=\"icon icon-leaf\" viewBox=\"0 0 64 64\"><defs><style>.a{stroke-miterlimit:10}<\/style><\/defs><path class=\"a\" d=\"M52 11 13 50m22-37v15h16\"><\/path><path class=\"a\" d=\"M52 11c6 24-16.72 47.29-33 32C7 22 29 10 52 11Z\"><\/path><\/svg>\n                                \n                              <span>Eco-plywood with natural wood glue<\/span>\n                            <\/span>\n                          <\/li>\n                        <\/ul>\n                     \n\n<ul class=\"sales-points\">\n                          <li class=\"sales-point\">\n                            <span class=\"icon-and-text\">\n                               <svg aria-hidden=\"true\" focusable=\"false\" role=\"presentation\" class=\"icon icon-circle-checkmark\" viewBox=\"0 0 64 64\"><path d=\"M52.68 24.48A22 22 0 1 1 47 15.93\"><\/path><path d=\"m21 32 8.5 8.5L57 13\"><\/path><\/svg>\n                                \n                              <span>Taxes &amp; duties are included for the United States, CA, the UK, and the EU Union 🇪🇺<\/span>\n                            <\/span>\n                          <\/li>\n                        <\/ul>\n\n<ul class=\"sales-points\">\n                          <li class=\"sales-point\">\n                            <span class=\"icon-and-text\">\n                               <svg aria-hidden=\"true\" focusable=\"false\" role=\"presentation\" class=\"icon icon-package\" viewBox=\"0 0 64 64\"><path d=\"M32 54.52 10 41.95v-19.9L32 9.48l22 12.57v19.9L32 54.52z\"><\/path><path d=\"M32 54.52v-19.9l22-12.57M32 34.62 10 22.05m31.7-7.03L21 28.33v8.38\"><\/path><\/svg>\n                                \n                              <span>Free delivery within 2 to 4 days in the United States and Canada<\/span>\n                            <\/span>\n                          <\/li>\n                        <\/ul>\n\n<ul class=\"sales-points\">\n                          <li class=\"sales-point\">\n                            <span class=\"icon-and-text\">\n                               <svg aria-hidden=\"true\" focusable=\"false\" role=\"presentation\" class=\"icon icon-lock\" viewBox=\"0 0 64 64\"><path d=\"M19.45 23.6v-3.2c0-7 5.89-11.75 12.55-11.75 7.21 0 12.55 5.49 12.55 11.75v3.2M10 23.6h44v31.75H10zm22 13.87v7.47\"><\/path><circle cx=\"32\" cy=\"35.87\" r=\"1.6\"><\/circle><\/svg>\n                                \n                              <span>Secure payments and free returns 30 days<\/span>\n                            <\/span>\n                          <\/li>\n                        <\/ul>\n\n<\/div>","width":"50%","alignment":"center"}},"image_AdPcEH":{"type":"image","settings":{"image":"shopify:\/\/shop_images\/indoor_fc0d0dd5-dabe-4bef-9939-b02ccd76ad13.jpg","link":"","width":"50%","alignment":"center"}}},"block_order":["liquid_d6CjgP","image_AdPcEH"],"settings":{"full_width":false,"space_around":false}},"advanced_content_Mphnyc":{"type":"advanced-content","blocks":{"image_tbBRNh":{"type":"image","settings":{"image":"shopify:\/\/shop_images\/5in1-montessori-climbing-frame-set-triangle-ladder-archrocker-slide-boardramp-netting-rope-cushion-436974.webp","link":"","width":"50%","alignment":"center"}},"liquid_L7e6wa":{"type":"liquid","settings":{"code":"<p>Elevate your child's play experience with our 5in1 Montessori Climbing Set, one of Goodevas' flagship offerings. Comprising the core elements of the climbing arch and the triangle ladder, this set is accentuated by the multifunctional climbing net, slide\/ramp  and сushion. Together, they open doors to imaginative play, fostering muscle strength, balance, coordination, refined motor skills, and boosted self-confidence. Ingeniously designed to interconnect, this set enables children to craft new play landscapes that evolve with their growth and creativity. Together, they open doors to imaginative play, fostering muscle strength, balance, coordination, refined motor skills, and boosted self-confidence. Ingeniously designed to interconnect, this set enables children to craft new play landscapes that evolve with their growth and creativity.<\/p>","width":"50%","alignment":"center"}}},"block_order":["image_tbBRNh","liquid_L7e6wa"],"custom_css":["p {font-size: 17px;}"],"settings":{"full_width":false,"space_around":true}},"rich_text_HNTkwV":{"type":"rich-text","blocks":{"heading_8aQP9n":{"type":"heading","settings":{"title":"Materials","heading_size":"h2"}},"text_phNpWJ":{"type":"text","settings":{"enlarge_text":true,"text":"<p>Every piece of this set stems from eco-friendly Latvian birch plywood and linden soft hardwood, emphasizing durability and elegance. Our meticulous sanding and polishing processes result in a splinter-free finish, prioritizing your child's safety. By integrating our signature blend of oils and waxes, we ensure the set's compatibility for indoor and controlled outdoor adventures, although it's advisable to keep it away from high humidity or extreme temperatures.<\/p>"}}},"block_order":["heading_8aQP9n","text_phNpWJ"],"settings":{"align_text":"center","narrow_column":false,"color_scheme":"2","divider":false}},"advanced_content_Qrd8wR":{"type":"advanced-content","blocks":{"image_3aTGqw":{"type":"image","settings":{"image":"shopify:\/\/shop_images\/5in1-montessori-climbing-frame-set-triangle-ladder-archrocker-slide-boardramp-netting-rope-cushion-885062_9a282f3f-6a69-4462-8e2e-377822c09455.webp","link":"","width":"50%","alignment":"center"}},"liquid_YhYkwT":{"type":"liquid","settings":{"code":"<ul>\n<li style=\"font-weight: 400;\"><strong>Complete Set<\/strong><\/li>\n<ul>\n<li style=\"font-weight: 400;\"><span style=\"font-weight: 400;\">Dimensions: 10 ft (302 cm)<\/span><\/li>\n<li style=\"font-weight: 400;\"><span style=\"font-weight: 400;\">Weight: 46.3 lb (21.9 kg)<\/span><\/li>\n<\/ul>\n<li style=\"font-weight: 400;\">\n<strong>Triangle Ladder<\/strong><span style=\"font-weight: 400;\"><br><\/span><span style=\"font-weight: 400;\">This double-sided ladder, when monitored by an adult, is a haven for little climbers, even those refining their coordination. With its expansive usable area, it can captivate multiple kids, making it an ideal piece for active children craving movement.<\/span>\n<\/li>\n<li style=\"font-weight: 400;\">\n<strong>Climbing Arch<\/strong><span style=\"font-weight: 400;\"><br><\/span><span style=\"font-weight: 400;\">A versatile play piece, the arch serves as a support for toddlers learning to stand. As your child grows, it becomes an advanced climbing tool or, when inverted, a unique balance board.<\/span>\n<\/li>\n<li style=\"font-weight: 400;\">\n<strong>Climbing Net<\/strong><span style=\"font-weight: 400;\"><br><\/span><span style=\"font-weight: 400;\">Crafted from natural wood and the soft, non-toxic multifilament polypropylene rope, this net offers both durability and safety. It's engineered to withstand pressure, ensuring kids can climb and step with confidence.<\/span>\n<\/li>\n<li style=\"font-weight: 400;\">\n<strong>Slide &amp; Climbing Ramp<\/strong><span style=\"font-weight: 400;\"><br><\/span><span style=\"font-weight: 400;\">A double-duty design showcases a smooth slide on one side and a climbing ramp with 4 planks on the other. This slide also doubles as a bridge, integrating seamlessly with other climbing structures to diversify play.<\/span>\n<\/li>\n<li style=\"font-weight: 400;\">\n<meta charset=\"utf-8\"> <strong><strong>Cushion for Climbing Arch<br><\/strong><\/strong>The soft and cloud-like cushion for the Climbing Arch provides the perfect surface for children to lie on while they enjoy their favorite hobby - rocking! The soft, light layers make for perfect lying and rocking where every position feels comfortable.<\/li>\n<\/ul>","width":"50%","alignment":"center"}}},"block_order":["image_3aTGqw","liquid_YhYkwT"],"custom_css":["li {font-size: 17px;}"],"settings":{"full_width":false,"space_around":true}},"advanced_content_9fBaNH":{"type":"advanced-content","blocks":{"liquid_MrExJh":{"type":"liquid","settings":{"code":"<ul>\n<li style=\"font-weight: 400;\">\n<strong>Climbing Net<\/strong><span style=\"font-weight: 400;\"><br><\/span><span style=\"font-weight: 400;\">Crafted from natural wood and the soft, non-toxic multifilament polypropylene rope, this net offers both durability and safety. It's engineered to withstand pressure, ensuring kids can climb and step with confidence.<\/span>\n<\/li>\n<li style=\"font-weight: 400;\">\n<strong>Slide &amp; Climbing Ramp<\/strong><span style=\"font-weight: 400;\"><br><\/span><span style=\"font-weight: 400;\">A double-duty design showcases a smooth slide on one side and a climbing ramp with 4 planks on the other. This slide also doubles as a bridge, integrating seamlessly with other climbing structures to diversify play.<\/span>\n<\/li>\n<li style=\"font-weight: 400;\">\n<meta charset=\"utf-8\"> <strong><strong>Cushion for Climbing Arch<br><\/strong><\/strong>The soft and cloud-like cushion for the Climbing Arch provides the perfect surface for children to lie on while they enjoy their favorite hobby - rocking! The soft, light layers make for perfect lying and rocking where every position feels comfortable.<\/li>\n<\/ul>","width":"75%","alignment":"center"}},"image_xUKY8z":{"type":"image","settings":{"image":"shopify:\/\/shop_images\/5in1-montessori-climbing-frame-set-triangle-ladder-archrocker-slide-boardramp-netting-rope-cushion-269943.webp","link":"","width":"33%","alignment":"center"}}},"block_order":["liquid_MrExJh","image_xUKY8z"],"disabled":true,"custom_css":["li {font-size: 17px;}"],"settings":{"full_width":false,"space_around":true}},"hotspots_9gVaby":{"type":"hotspots","blocks":{"product_KWetQM":{"type":"product","settings":{"featured_product":"2in1-montessori-climbing-set-triangle-ladder-slide-board-ramp-beige","vertical":20,"horizontal":31}},"product_pUJtzx":{"type":"product","settings":{"featured_product":"climbing-arch-cushion-montessori-climbers-for-toddlers","vertical":55,"horizontal":78}}},"block_order":["product_KWetQM","product_pUJtzx"],"settings":{"title":"Shop separately","heading_size":"h2","heading_position":"left","image":"shopify:\/\/shop_images\/5in1-montessori-climbing-frame-set-triangle-ladder-archrocker-slide-boardramp-netting-rope-cushion-741950.webp","indent_image":true,"image_position":"right","hotspot_style":"bag","hotspot_color":"#000000"}},"1697369884712960f2":{"type":"apps","blocks":{"5c95190f-85af-410d-a84a-d5bcab0553e5":{"type":"shopify:\/\/apps\/yotpo-product-reviews-ugc\/blocks\/reviews\/eb7dfd7d-db44-4334-bc49-c893b51b36cf","settings":{"product":"{{product}}"}}},"block_order":["5c95190f-85af-410d-a84a-d5bcab0553e5"],"settings":{"full_width":false,"space_around":true}},"1665670604c4b36c84":{"type":"apps","settings":{"full_width":false,"space_around":true}},"recommendations":{"type":"product-recommendations","settings":{"product_recommendations_heading":"You may also like","related_count":6,"products_per_row":3}},"recently-viewed":{"type":"recently-viewed","settings":{}},"more-products-vendor":{"type":"more-products-vendor","settings":{"products_per_row":3,"max_products":3}},"more-products-collection":{"type":"more-products-collection","settings":{"products_per_row":3,"max_products":3}},"collection-return":{"type":"collection-return","settings":{"color_scheme":"2"}}},"order":["main","sub","1700591428fe934e1e","slideshow_split_iM3mVC","scrolling_text_A4EmxT","featured_product_jLmbaE","advanced_content_HUw6yc","advanced_content_Mphnyc","rich_text_HNTkwV","advanced_content_Qrd8wR","advanced_content_9fBaNH","hotspots_9gVaby","1697369884712960f2","1665670604c4b36c84","recommendations","recently-viewed","more-products-vendor","more-products-collection","collection-return"]}